sparsemixer/__init__.py
sparsemixer/sparsemixer.py
sparsemixer/switchgate.py
sparsemixer-0.0.0.dist-info/LICENSE
sparsemixer-0.0.0.dist-info/METADATA
sparsemixer-0.0.0.dist-info/WHEEL
sparsemixer-0.0.0.dist-info/top_level.txt
sparsemixer-0.0.0.dist-info/RECORD
