Metadata-Version: 2.1
Name: sparsemixer
Version: 0.0.0
Summary: SparseMixer Algorithm
Home-page: https://github.com/microsoft/SparseMixer
Author: Lucas Liu
Author-email: llychinalz@gmail.com
License: MIT
Platform: UNKNOWN
Classifier: Development Status :: 2 - Pre-Alpha
Classifier: Intended Audience :: Developers
Classifier: Natural Language :: English
Classifier: Programming Language :: Python :: 3.7
Classifier: Programming Language :: Python :: 3.8
Classifier: Programming Language :: Python :: 3.9
License-File: LICENSE
Requires-Dist: torch
